{
  "Rows": {
    "200101": {
      "Cuid": 200101,
      "Harbourid": 200101,
      "Partid": 1001,
      "Recommendboat": [
        4,
        0,
        0,
        0,
        1
      ],
      "LangStringTable": {
        "Shortname": "出逃-第一幕"
      }
    },
    "200102": {
      "Cuid": 200102,
      "Harbourid": 200102,
      "Partid": 1002,
      "Recommendboat": [
        4,
        0,
        0,
        0,
        1
      ],
      "LangStringTable": {
        "Shortname": "神秘人偶-第一幕"
      }
    },
    "200103": {
      "Cuid": 200103,
      "Harbourid": 200103,
      "Partid": 1002,
      "Recommendboat": [
        4,
        0,
        0,
        0,
        1
      ],
      "LangStringTable": {
        "Shortname": "神秘人偶-第二幕"
      }
    },
    "200104": {
      "Cuid": 200104,
      "Harbourid": 200104,
      "Partid": 1002,
      "Recommendboat": [
        4,
        0,
        0,
        0,
        1
      ],
      "LangStringTable": {
        "Shortname": "神秘人偶-第三幕"
      }
    },
    "200105": {
      "Cuid": 200105,
      "Harbourid": 200105,
      "Partid": 1003,
      "Recommendboat": [
        4,
        0,
        0,
        0,
        1
      ],
      "LangStringTable": {
        "Shortname": "漁村之夜-第一幕"
      }
    },
    "200201": {
      "Cuid": 200201,
      "Harbourid": 200201,
      "Partid": 1003,
      "Recommendboat": [
        4,
        0,
        0,
        0,
        1
      ],
      "LangStringTable": {
        "Shortname": "漁村之夜-第二幕"
      }
    },
    "200202": {
      "Cuid": 200202,
      "Harbourid": 200202,
      "Partid": 1003,
      "Recommendboat": [
        4,
        0,
        0,
        0,
        1
      ],
      "LangStringTable": {
        "Shortname": "漁村之夜-第三幕"
      }
    },
    "200203": {
      "Cuid": 200203,
      "Harbourid": 200203,
      "Partid": 1003,
      "Recommendboat": [
        4,
        0,
        0,
        0,
        1
      ],
      "LangStringTable": {
        "Shortname": "漁村之夜-第四幕"
      }
    },
    "200204": {
      "Cuid": 200204,
      "Harbourid": 200204,
      "Partid": 1004,
      "Recommendboat": [
        4,
        0,
        0,
        0,
        1
      ],
      "LangStringTable": {
        "Shortname": "騷亂-第一幕"
      }
    },
    "200205": {
      "Cuid": 200205,
      "Harbourid": 200205,
      "Partid": 1004,
      "Recommendboat": [
        4,
        0,
        0,
        0,
        1
      ],
      "LangStringTable": {
        "Shortname": "騷亂-第二幕"
      }
    },
    "200206": {
      "Cuid": 200206,
      "Harbourid": 200206,
      "Partid": 1004,
      "Recommendboat": [
        4,
        0,
        0,
        0,
        1
      ],
      "LangStringTable": {
        "Shortname": "騷亂-第三幕"
      }
    },
    "200207": {
      "Cuid": 200207,
      "Harbourid": 200207,
      "Partid": 1004,
      "Recommendboat": [
        4,
        0,
        0,
        0,
        1
      ],
      "LangStringTable": {
        "Shortname": "騷亂-第四幕"
      }
    },
    "200301": {
      "Cuid": 200301,
      "Harbourid": 200301,
      "Partid": 1005,
      "Recommendboat": [
        4,
        0,
        0,
        0,
        1
      ],
      "LangStringTable": {
        "Shortname": "八百萬神-第一幕"
      }
    },
    "200302": {
      "Cuid": 200302,
      "Harbourid": 200302,
      "Partid": 1005,
      "Recommendboat": [
        4,
        0,
        0,
        0,
        1
      ],
      "LangStringTable": {
        "Shortname": "八百萬神-第二幕"
      }
    },
    "200303": {
      "Cuid": 200303,
      "Harbourid": 200303,
      "Partid": 1005,
      "Recommendboat": [
        4,
        0,
        0,
        0,
        1
      ],
      "LangStringTable": {
        "Shortname": "八百萬神-第三幕"
      }
    },
    "200304": {
      "Cuid": 200304,
      "Harbourid": 200304,
      "Partid": 1005,
      "Recommendboat": [
        4,
        0,
        0,
        0,
        1
      ],
      "LangStringTable": {
        "Shortname": "八百萬神-第四幕"
      }
    },
    "200305": {
      "Cuid": 200305,
      "Harbourid": 200305,
      "Partid": 1005,
      "Recommendboat": [
        4,
        0,
        0,
        0,
        1
      ],
      "LangStringTable": {
        "Shortname": "八百萬神-第五幕"
      }
    }
  }
}